W3schoolPythonJiaochengFix1/README.md
W3schoolPythonJiaochengFix1/__init__.py
W3schoolPythonJiaochengFix1/__main__.py
W3schoolPythonJiaochengFix1/file.epub
W3schoolPythonJiaochengFix1/index.html
W3schoolPythonJiaochengFix1/css/__init__.py
W3schoolPythonJiaochengFix1/css/annotations.css
W3schoolPythonJiaochengFix1/css/main.css
W3schoolPythonJiaochengFix1/css/normalize.css
W3schoolPythonJiaochengFix1/css/popup.css
W3schoolPythonJiaochengFix1/font/__init__.py
W3schoolPythonJiaochengFix1/font/fontello.eot
W3schoolPythonJiaochengFix1/font/fontello.svg
W3schoolPythonJiaochengFix1/font/fontello.ttf
W3schoolPythonJiaochengFix1/font/fontello.woff
W3schoolPythonJiaochengFix1/img/__init__.py
W3schoolPythonJiaochengFix1/img/annotator-glyph-sprite.png
W3schoolPythonJiaochengFix1/img/annotator-icon-sprite.png
W3schoolPythonJiaochengFix1/img/apple-touch-icon.png
W3schoolPythonJiaochengFix1/img/cancelfullscreen.png
W3schoolPythonJiaochengFix1/img/close.png
W3schoolPythonJiaochengFix1/img/fullscreen.png
W3schoolPythonJiaochengFix1/img/loader.gif
W3schoolPythonJiaochengFix1/img/menu-icon.png
W3schoolPythonJiaochengFix1/img/save.png
W3schoolPythonJiaochengFix1/img/saved.png
W3schoolPythonJiaochengFix1/img/settings-s.png
W3schoolPythonJiaochengFix1/img/settings.png
W3schoolPythonJiaochengFix1/img/star.png
W3schoolPythonJiaochengFix1/js/__init__.py
W3schoolPythonJiaochengFix1/js/epub.js
W3schoolPythonJiaochengFix1/js/epub.min.js
W3schoolPythonJiaochengFix1/js/epub.min.map
W3schoolPythonJiaochengFix1/js/hooks.min.js
W3schoolPythonJiaochengFix1/js/hooks.min.map
W3schoolPythonJiaochengFix1/js/reader.js
W3schoolPythonJiaochengFix1/js/reader.js.map
W3schoolPythonJiaochengFix1/js/reader.min.js
W3schoolPythonJiaochengFix1/js/reader.min.map
W3schoolPythonJiaochengFix1/js/hooks/__init__.py
W3schoolPythonJiaochengFix1/js/hooks/extensions/__init__.py
W3schoolPythonJiaochengFix1/js/hooks/extensions/highlight.js
W3schoolPythonJiaochengFix1/js/libs/__init__.py
w3school_python_jiaocheng_fix1-2025.3.24.0.dist-info/METADATA
w3school_python_jiaocheng_fix1-2025.3.24.0.dist-info/WHEEL
w3school_python_jiaocheng_fix1-2025.3.24.0.dist-info/entry_points.txt
w3school_python_jiaocheng_fix1-2025.3.24.0.dist-info/top_level.txt
w3school_python_jiaocheng_fix1-2025.3.24.0.dist-info/RECORD
